historist-0.1.0.dev2.dist-info/DESCRIPTION.rst
historist-0.1.0.dev2.dist-info/metadata.json
historist-0.1.0.dev2.dist-info/top_level.txt
historist-0.1.0.dev2.dist-info/WHEEL
historist-0.1.0.dev2.dist-info/entry_points.txt
historist-0.1.0.dev2.dist-info/METADATA
historist-0.1.0.dev2.dist-info/RECORD
historist/historist.py
historist/__init__.py
historist/database_interface.py
historist/cli.py
