Metadata-Version: 2.0
Name: historist
Version: 0.1.0.dev2
Summary: activity logger
Home-page: http://github.com/sina33/historist
Author: Sina Saeedi
Author-email: sina.saeedi@outlook.com
License: MIT
Keywords: archive,events,logs
Platform: UNKNOWN
Requires-Dist: sqlalchemy (>=1.0.9)
